dbt_ai/__init__.py
dbt_ai/ai.py
dbt_ai/config.py
dbt_ai/dbt.py
dbt_ai/helper.py
dbt_ai/main.py
dbt_ai/models.py
dbt_ai/py.typed
dbt_ai/report.py
dbt_ai/templates/report_template.html
dbt_ai-0.4.0.dist-info/LICENSE
dbt_ai-0.4.0.dist-info/METADATA
dbt_ai-0.4.0.dist-info/WHEEL
dbt_ai-0.4.0.dist-info/entry_points.txt
dbt_ai-0.4.0.dist-info/top_level.txt
dbt_ai-0.4.0.dist-info/RECORD
