Metadata-Version: 2.1
Name: dbt-ai
Version: 0.4.0
Summary: AI-powered dbt helper with modern GPT models and enhanced prompts
Requires-Python: >=3.10
License-File: LICENSE
Requires-Dist: dbt-snowflake~=1.4
Requires-Dist: openai<2.0,>=1.0
Requires-Dist: pydantic<3.0,>=2.0
Requires-Dist: pyyaml~=6.0
Requires-Dist: markdown2~=2.4
Requires-Dist: pyvis~=0.3.2
Requires-Dist: plotly~=5.14
Requires-Dist: numpy~=1.24
Provides-Extra: dev
Requires-Dist: black~=23.1; extra == "dev"
Requires-Dist: build~=0.10; extra == "dev"
Requires-Dist: pre-commit~=3.0; extra == "dev"
Requires-Dist: ruff~=0.0.254; extra == "dev"
Requires-Dist: twine~=4.0; extra == "dev"
Requires-Dist: pytest~=7.3; extra == "dev"
